{
  "id": "49937469",
  "category": "HR",
  "resume_text": "HR ASSISTANT \n\nHIGHLIGHTS Interviewing expertise Employee Relations Manager Coaching and training Event management Employee Handbook development Staffing and recruiting professional Off-boarding Accomplishments Organized HR Generalist effective at record maintenance and assuring compliance with government employment regulations at all times. Personable HR Generalist versed in recruiting top employees to automotive companies and innovative start-ups. \n\nEXPERIENCE with public speaking on college campuses to attract new talent. \n\nEXPERIENCE HR Assistant September 2015 to Current Company Name － City , State Advise managers on organizational policy matters andrecommend needed changes. Conduct new employee orientatio to foster positive attitudes toward organizational objectives. Identify staff vacancies and recruite,interview and select aplicants. Serve as a link between management and employees by handling questions, interpreting and administering contracts and help resolve work-related problems. Address inquires from employees and management regarding new-hire activity and ongoing employee relation issues. Created and implimented the exit interview program process. Advise top management on apropriate employee corrective actions. Create and modify job discriptions within all departments. Work with senior-level management to create fair and consistent HR policies and procedures. Work with HR advisors and HR representatives on establishing consistent hiring practices. Create and manage more than 100 confidential personnel records. Facilitate monthly meetings to develpo strategies that will positively influence workplace relationships. Suport 77 employees at all levels, including executive leadership. \n\nEXPERIENCE Specialist November 2011 to September 2015 Company Name － City , State Prevented store losses using awareness, attention to detail and integrity. Cross-trained and provided back-up for other customer services representatives when needed. Generated sales inventory reports in Excel with data from a variety of sources, maintaining a 100% accuracy rate. Prepared and sold a broad range of customized merchandise to individuals and commercial accounts. Resolved product issues and shared benefits of new technology. Successfully interacted with customers and retail buyers to expedite orders. Compilied weekly monetary reports and records for store managers. Maintained adequate cash supply in cash drawers in multiple checkout stations. Managed cash stock and inventory balances accurately. Clerk/Store Manager June 2002 to January 2012 Company Name － City , State Was promoted to store manager after 3 weeks as a clerk. Managed a team of 7 professionals. Reduced and controlled expenses by developing an inventory controll process that was later used in all local stores. Delivered excellent customer service by greeting and assisting each customer. Addressed customer inquires and resolved complaints. Designed and implimented customer satisfaction metrics. Stocked and restocked inventory when shipments were received. Reorganized the sales floor to meet company demands. Directed and supervised employees engaged in sales, inventory-taking and reconciling cash receipts. Determined staff promotions and demotions, and terminated employees when necessary. Completed weekly schedules according to payroll policies. Maintained daily records of all transactions. Wrote order suply requests to replenish merchandise. Trained staff to deliver outstanding customer service. Addressed and corrected sales staff communication issues in a tactful and effective manner. Student worker/Multiple departments May 2004 to May 2011 Company Name － City , State Inspired students to translate their academic interests into the real world by taking positive actions. Initiated throught-provoking classroom discussions to help students develop their critical thinking abilities. Emphasized the importance of academic honesty with students and instructed them on proper citation of research sources. Maintained athletics yearly budget with 100% accuracy. Conseled undergraduates in regard to educational and professional goals. Proctored yearly final exams at the end of each semester. Maintained strong ties with alumni to foster long-term suport with the school. HR Generalist January 2004 to May 2007 Company Name － City , State Conducted benefits administration for 30 benefit-eligible employees. Designed the emoployee performance evaluation process and merit program. Addressed inquires from employees and management regarding new-hire activity and ongoing employee relation issues. Created and implimented the exit interview programprocess. Advise top management on apropriate employee corrective actions. Created and modified job discriptions within all departments. Worked with senior-level management to create fair and consistent HR policies and procedures. Developed 2 employee handbooks, including design and layout. Guided the startup and management of all HR operations, systems and programs for a new location within the company. Supported 30 employees at al levels, including executive leadership. \n\nEDUCATION BACHELOR OF ARTS : ORGANIZATIONAL LEADERSHIP MANAGEMENT AND HUMAN RESOURCE MANAGEMENT , 2011 Lourdes College － City , State ORGANIZATIONAL LEADERSHIP MANAGEMENT AND HUMAN RESOURCE MANAGEMENT ASSOCIATE OF ARTS : 2006 Lourdes College － City , State Interests Swimming, bike riding, camping, crocheting, crafts, and a variety of family activities. \n\nSKILLS academic, A.I., attention to detail, back-up, benefits, benefits administration, budget, cash receipts, Coaching, contracts, critical thinking, customer satisfaction, customer services, excellent customer service, customer service, Employee Relations, Event management, hiring, HR, inventory, layout, leadership, meetings, Excel, organizational \n\nSKILLS, organizational, payroll, personnel, policies, problem-solving, reconciling, recruiting, research, retail, sales, Staffing, store manager, employee handbooks",
  "education": {
    "degree_level": "bachelor",
    "degree_title": "Bachelor of Arts",
    "field": "Organizational Leadership Management and Human Resource Management",
    "year": "2011",
    "institution": "Lourdes College"
  },
  "work_experience": {
    "job_title": "HR Assistant",
    "company": "Company Name",
    "start_date": "September 2015",
    "end_date": "Current",
    "responsibilities": "Advised managers on organizational policy matters and recommended needed changes. Conducted new employee orientation to foster positive attitudes toward organizational objectives. Identified staff vacancies and recruited, interviewed, and selected applicants. Served as a link between management and employees by handling questions, interpreting and administering contracts, and resolving work-related problems. Addressed inquiries from employees and management regarding new-hire activity and employee relations. Created and implemented the exit interview program process. Advised top management on appropriate employee corrective actions. Created and modified job descriptions within all departments. Worked with senior management to establish HR policies and consistent hiring practices. Created and managed more than 100 confidential personnel records. Facilitated monthly meetings to develop workplace relationship strategies. Supported 77 employees at all levels, including executive leadership."
  },
  "skills": {
    "name": "Interviewing expertise, Employee Relations, Manager coaching and training, Event management, Employee handbook development, Staffing and recruiting, Off-boarding, Benefits administration, Coaching, Contracts, Customer service, Employee handbooks, Hiring, HR, Inventory, Leadership, Meetings, Excel, Organizational skills, Payroll, Personnel, Policies, Problem-solving, Recruiting, Research, Retail, Sales, Staffing, Store management",
    "years_experience": ""
  },
  "language": {
    "name": "",
    "level": ""
  },
  "certifications": {
    "name": "",
    "issuing_organization": "",
    "date_obtained": "",
    "valid_until": ""
  },
  "projects": {
    "name": "Exit Interview Program Implementation",
    "description": "Created and implemented the exit interview program process to improve employee feedback and off-boarding procedures.",
    "technologies_used": "",
    "role": "HR Assistant",
    "duration": ""
  },
  "awards": {
    "name": "",
    "issuing_organization": "",
    "date_received": "",
    "description": ""
  },
  "voluntary_experience": {
    "role": "",
    "organization": "",
    "start_date": "",
    "end_date": "",
    "description": ""
  },
  "publications": {
    "title": "",
    "publication_venue": "",
    "date_published": "",
    "url": ""
  },
  "hobbies": {
    "name": "Swimming, bike riding, camping, crocheting, crafts, family activities",
    "description": "Enjoys swimming, biking, camping, crocheting, crafts, and various family activities."
  },
  "role_fit": "strong",
  "reasoning": "meaningful project for the role"
}