{
  "id": "24508725",
  "category": "HR",
  "resume_text": "FIELD HR ASSOCIATE \n\nSUMMARY Reliable HR Field Associate with a Master's of science in Human Resource management emphasis as a Generalist. Passionate and motivated with a drive for excellence. Handles tasks with accuracy and efficiency. \n______________________________________________________________________________ \n\nSKILLS\n*Verbal and written communication \n\nSKILLS \n*Time management and organization \n\nSKILLS\n*Powerpoint presentations\n*Flexible \n*Recruiting\n*Investigation training\n*Employee engagement\n*Ability to develop and execute recruitment strategies\n*Analyze data and recommend opportunities for improvement \n*\n\nEXPERIENCE in preparing for audits\n*Assisted in the hiring process by screening resumes-Select interview process certified via FedEx Ground\n* Demonstrated ability to interact effectively with employees. \n* Ability to anticipate and identify problems and use sound judgment and fact based analysis to develop effective and efficient solutions. \n* Software \n\nSKILLS, including use of Microsoft Office software and web-based applications. \n* Ability to work day, evening and overnight hours as business needs dictate. I am sending my resume to apply for the position of HR Generalist at AccruePartners, which was posted on LinkedIn by Mr. Luther Hardings.\nAs you can see in my resume, I possess over 6 years of \n\nEXPERIENCE working as an HR professional at two renowned companies in the US, which according to your job requirements, are two most important points.\nMy qualifications are the exact match to your job descripton:\n* Capable of carrying out the recruitment process efficiently while maintaining quality standard.\nEvidence: Screened 1500 resumes, Interviewed 500 candidates and hired 150 from this pool for the new call center setup at ABC Company in only 25 days.\n* Able to consistently draft new and improve HR policies and procedures to boost staff motivation.\nEvidence: With new and improved policies and procedures and resolving all staff related issues, increased employee motivation which resulted in increased retention percentages over the years that I worked at ABC Company.\n* Proficient in executing effective employee performance evaluations and subsequent performance based appraisals Evidence: Performed employee evaluation process and appraisals on quarterly basis under the supervision of the HR manager at Emerson Network Power Inc.\nWith my passion for HR work, superb management \n\nSKILLS and the urge for performing with quality, I would be able to contribute to your HR Department effectively. Thank you very much for your consideration. I look forward to meeting with you soon.\nBest regards,\n(Signature)\nNathan Talovsky Enclosure.\n*Mar \n*Human Resource Coordinator Thank You Email after Interview \nA thank you letter or email is a business norm which every candidate has to follow behind interview with a prospective employer. Thank you emails are a courtesy that you should indulge in.\nLet us take the example of a candidate who has given an interview for the position of a Human Resource Coordinator. He or she will need to ensure that an email is sent which reiterates his or her interest in the job and thanks the interviewer for his time.\n_______________________________________________________________________________ Human Resource Coordinator Thank You Email To: Jennifer Miller [Email]\nSubject | Re: Human Resource Coordinator - Kimberly Perez Dear Ms. Miller,\nPlease accept my heartiest appreciation for taking out the time and interviewing me for the position of a human resource coordinator last Wednesday. It was an absolute pleasure meeting you in person and discussing the possibility of my working with ABC Company.\nI am very enthusiastic about joining ABC Company, meeting you at the interview has solidified my interest even further. As a keen candidate for this position, I have much to offer in terms of meticulous attention to detail while carrying out HR duties, organizing and scheduling on boarding activities for new hires and ensuring compliance for FMLA. My demonstrated ability to work in a fast paced environment will be evident from my work in responding to employee requests and coordinating general administrative tasks. Responsible for addressing employee relations concerns and recruiting for open positions at assigned facilities. Must be able to travel up to 75% of the time with overnight stays required as business needs dictate. \nEssential Functions \n* Ensures compliance with all employment laws, regulations, and FedEx Ground policies, procedures, and processes. \n* Identifies employee relations issues and resolves as appropriate. Provides Human Resource (HR) advice to management and responds to employee inquiries. \n* Conducts investigations in a timely and appropriate manner. Identifies the issues and parties involved and provides a thorough and accurate investigative report with appropriate recommendation(s). \n* Maintains an HR presence in assigned facilities by engaging all levels of employees through activities to include, but not limited to, dock walks, engagement meetings, and/or special events. \n* Leads the development and execution of the recruitment strategies while managing costs to budget. This includes, but is not limited to, recruitment activities, peak planning, and participating in outreach events. Builds and maintains effective relationships with schools and community-based organizations. \n* Analyzes data and provides recommendations to management for improvement initiatives. \n* Prepares, audits, and monitors Affirmative Action Plans. \n* Screens resumes of internal and external candidates for non package handler positions, participates in the panel interview process, and makes recommendations to the hiring manager regarding final selection decisions. \n* Properly and timely dispositions applicants and jobs by effectively utilizing applicant tracking system. \n* Assists management with development of job offers, which includes gaining appropriate approvals. \n* Ensures all new employees are on-boarded effectively. \n* Manages participation in all government-sponsored tax credit programs. \n* Facilitates and conducts training. \n* Participates in hub and station assessments and assists with strategic planning solutions. \n* Participates in Operations' staff meetings. \nMinimum \n\nEDUCATION \n* Bachelor's Degree in Human Resources, Business, Communications, or related discipline required. In addition to the two (2) years Minimum \n\nEXPERIENCE, a high school degree or GED and additional four (4) years HR Generalist, employee relations or recruiting (to include FXG/FXSP Field HR Associate) will be considered equivalent to a Bachelor's Degree. \nMinimum \n\nEXPERIENCE \n* Two (2) years professional HR \n\nEXPERIENCE in HR Generalist, employee relations or recruiting (to include FXG/FXSP Field HR Associate) required or related area. \nRequired \n\nSKILLS, Abilities and / or Licensure \n* Verbal and written communication \n\nSKILLS necessary to explain complex and/or confidential information and communicate with all levels of management. \n* Time management and organizational \n\nSKILLS necessary to manage multiple \n\nPROJECTS, appropriately prioritize workload, plan for resources to meet deadlines and goals, and work independently in responding to day-to-day functional needs. \n* Presentation \n\nSKILLS necessary to facilitate training and/or deliver informational sessions to groups and/or individuals. \n* Demonstrated ability to interact effectively with employees. \n* Ability to anticipate and identify problems and use sound judgment and fact-based analysis to develop effective and efficient solutions. \n* Software \n\nSKILLS, including use of Microsoft Office software and web-based applications. \n* Ability to work day, evening and overnight hours as business needs dictate. \n* Professional in Human Resources (PHR) Senior Professional in Human Resources (SPHR) certification preferred. \n% of Travel for the Position \n50%-75% \nAddress \n\nHIGHLIGHTS Human Resource Generalist PROFILE: Avid professional with over 6 years of \n\nEXPERIENCE in a fast paced Human Resource department. Incomparable ability to prioritize and execute multiple HR \n\nPROJECTS and deadlines concurrently. Unmatchable organizational, time management and interpersonal \n\nSKILLS. Proficient in administering corporate HR initiatives, providing a broad level of counseling on recruitment, employee relations, retention and training programs and handling complex situations with professionalism and confidentiality. Expert knowledge of local, state, district and country laws influencing personnel actions. AREAS OF EXPERTISE Job analysis Market pricing Salary administration Performance review Employee orientation HR policies development Benefits administration Recruitment coordination ADP PeopleSoft HRIS systems MS Office: Word, Excel, PowerPoint Visio \n\nEXPERIENCE Field HR Associate January 2015 to Current Company Name Ensures compliance with all employment laws, regulations, and FedEx Ground policies, procedures, and processes. Identifies employee relations issues and resolves as appropriate. Provides Human Resource (HR) advice to management and responds to employeeinquiries. Conducts investigations in a timely and appropriate manner. Identifies the issues and parties involved and provides a thorough and accurate investigative report with appropriate recommendation(s). Maintains an HR presence in assigned facilities by engaging all levels of employees through activities to include, but not limited to, dock walks, engagement meetings, and/or special events. Leads the development and execution of the recruitment strategies while managing costs to budget. This includes, but is not limited to, recruitment activities, peak planning, and participating in outreach events. Builds and maintains effective relationships with schools and community-based organizations. Analyzes data and provides recommendations to management for improvement initiatives. Prepares, audits, and monitors Affirmative Action Plans. Screens resumes of internal and external candidates for non package handler positions, participates in the panel interview process, and makes recommendations to the hiring manager regarding final selection decisions. Properly and timely dispositions applicants and jobs by effectively utilizing applicant tracking system. Assists management with development of job offers, which includes gaining appropriate approvals. Ensures all new employees are on-boarded effectively. Manages participation in all government-sponsored tax credit programs. Facilitates and conducts training. Participates in hub and station assessments and assists with strategic planning solutions. Participates in Operations' staff meetings. Financial Aid Counselor May 2013 to November 2013 Company Name － City , State Analyze applicants' financial status, credit, and property evaluations to determine feasibility of granting loans. Interview applicants and request specified information for loan applications. Establish payment priorities according to credit terms and interest rates to reduce clients' overall costs. Contact applicants or creditors to resolve questions about applications or to assist with completion of paperwork. Inform individuals and groups about the financial assistance available to college or university students. Maintain current knowledge of credit regulations. Match students' needs and eligibility with available financial aid programs to provide informed recommendations. Review billing for accuracy. Assist in selection of financial award candidates using electronic databases to certify loan eligibility. Compare data on student aid applications with eligibility requirements of assistance programs. Counsel clients on personal and family financial problems, such as excessive spending or borrowing of funds. Financial Aid Advisor June 2010 to May 2012 Company Name － City , State Check loan agreements to ensure that they are complete and accurate, according to policies. Analyze applicants' financial status, credit, and property evaluations to determine feasibility of granting loans. Interview applicants and request specified information for loan applications. Contact applicants or creditors to resolve questions about applications or to assist with completion of paperwork. Inform individuals and groups about the financial assistance available to college or university students. Maintain current knowledge of credit regulations. Match students' needs and eligibility with available financial aid programs to provide informed recommendations. Assist in selection of financial award candidates using electronic databases to certify loan eligibility. Maintain and review account records, updating and categorizing them according to status changes. Compare data on student aid applications with eligibility requirements of assistance programs. Counsel clients on personal and family financial problems, such as excessive spending or borrowing of funds. Review accounts to determine write-offs for collection agencies. Human Resource Coordinator November 2007 to March 2010 Company Name － City , State Administered employee benefit plans including new hire orientation program, open enrollment process and wellness program. Prepared, presented and distributed employee communications, publications and announcements. General Human Resources Functions: Administered policies and programs relating to all phases of human resources activity including HR planning, recruitment, training and development, employee performance evaluation and appraisals, firing processes, etc. Along with these, maintained knowledge of legal requirements and government reporting regulations affecting human resources. Administration of Employee Relocation: Worked independently with candidates to manage the relocation process and coordinated all arrangements to include: house hunting trip, travel, temporary housing arrangements and movers. Key Accomplishments Developed and maintained various HRIS systems to improve management of tracking of employee relations issues, leaves, corrective actions and unemployment. \n\nEDUCATION Master of Science : Human Resource Management , July 2014 Strayer University － State Human Resource Management Bachelor of Arts : Human Resource Management , June 2011 Strayer University － State Human Resource Management B.B.A : Human Resource Management , 2005 University of Clifton － City , State Human Resource Management PHR certification - HR Certification Institute, Pomona, NY. [ : 2006 ]\nHRCI certification : 2006 HR Certification Institute － City , State Affiliations Member of Alpha Chi National Honor Society Member of National Society for Collegiate Scholars Personal Information Please feel free to call me at (217) 097-5477 if you need any further information from me that will assist you in processing my application. I am very excited at the prospect of working for your company and look forward to seeing you again soon. Thank you for your time and consideration.\nBest Regards,\n(E. Signature)\nAnthony Nelson 88 Malard Drive Clarksville, TN 93002 http://coverlettersandresume.com/hr/human-resource-coordinator-thank-you-email-after-interview/\nAuto req ID \n114760BR \nPosting Title \nField HR Generalist I - II \nPosition Type \nFull Time \n\nSKILLS ADP, Avid, Benefits administration, billing, budget, interpersonal \n\nSKILLS, counseling, credit, clients, databases, documentation, employee communications, employee relations, special events, fast, filing, financial, firing, funds, government, Hiring, HRIS, hub, Human Resources management, Human Resource, Human Resources, HR, Information Systems, Job analysis, leadership, legal, managing, Market, meetings, Excel, MS Office, office, PowerPoint, Word, monitors, organizational, payroll, peak, PeopleSoft, performance appraisals, personnel, policies, presenting, pricing, processes, publications, Recruitment, reporting, strategic planning, tax, phone, time management, training programs, Visio, written Additional Information Please feel free to call me at (217) 097-5477 if you need any further information from me that will assist you in processing my application. I am very excited at the prospect of working for your company and look forward to seeing you again soon. Thank you for your time and consideration.\nBest Regards,\n(E. Signature)\nAnthony Nelson 88 Malard Drive Clarksville, TN 93002 http://coverlettersandresume.com/hr/human-resource-coordinator-thank-you-email-after-interview/\nAuto req ID \n114760BR \nPosting Title \nField HR Generalist I - II \nPosition Type \nFull Time 1101 E Cleveland Road \nCity \nHutchins \nState \nTexas \nZip Code \n75141 \nSearch Engine Description \nHuman Resources \nDomicile Location \nP753 \nEEO Statement \nFedEx Ground is an equal opportunity / affirmative action employer (Minorities/Females/Disability/Veterans) committed to a diverse workforce",
  "education": {
    "degree_level": "master",
    "degree_title": "Master of Science",
    "field": "Human Resource Management",
    "year": "July 2014",
    "institution": "Strayer University"
  },
  "work_experience": {
    "job_title": "Field HR Associate",
    "company": " ",
    "start_date": "January 2015",
    "end_date": "Current",
    "responsibilities": "Ensures compliance with all employment laws, regulations, and FedEx Ground policies, procedures, and processes. Identifies employee relations issues and resolves as appropriate. Provides HR advice to management and responds to employee inquiries. Conducts investigations and provides reports with recommendations. Leads recruitment strategies, manages costs, builds community relationships, prepares and audits Affirmative Action Plans, screens resumes, participates in panel interviews, assists with job offers, ensures onboarding, manages participation in tax credit programs, facilitates and conducts training, and participates in operational assessments and staff meetings."
  },
  "skills": {
    "name": "Verbal and written communication, Time management, Organization, PowerPoint presentations, Recruiting, Investigation training, Employee engagement, Recruitment strategies, Data analysis, Auditing, Microsoft Office, HRIS, ADP, PeopleSoft, Benefits administration, Employee relations, Job analysis, Market pricing, Salary administration, Performance review, Employee orientation, HR policies development, Payroll, Training programs",
    "years_experience": "6"
  },
  "language": {
    "name": "",
    "level": ""
  },
  "certifications": {
    "name": "PHR certification",
    "issuing_organization": "HR Certification Institute",
    "date_obtained": "2006",
    "valid_until": ""
  },
  "projects": {
    "name": "",
    "description": "",
    "technologies_used": "",
    "role": "",
    "duration": ""
  },
  "awards": {
    "name": "",
    "issuing_organization": "",
    "date_received": "",
    "description": ""
  },
  "voluntary experience": {
    "role": "Member",
    "organization": "Alpha Chi National Honor Society; National Society for Collegiate Scholars",
    "start_date": "",
    "end_date": "",
    "description": ""
  },
  "publications": {
    "title": "",
    "publication_venue": "",
    "date_published": "",
    "url": ""
  },
  "hobbies": {
    "name": "",
    "description": ""
  }
}