{
  "id": "20993320",
  "category": "HR",
  "resume_text": "HR COORDINATOR \n\nSUMMARY From my first job as a retail salesperson, I had a passion for leadership and the development of others.  As a Human Resources professional I have had the privilege of working with new staff members to help them be successful in the organization. My Human Resources \n\nEXPERIENCE is comprised of Generalist responsibilities where I have been able to contribute to the betterment of the organization and play a key role in increasing retention for my employer.   \n\nHIGHLIGHTS HR policies and procedures expertise Employee handbook development Staff training and development New employee on-boarding Off-boarding Employment law knowledge Payroll expertise Benefits administrator Organized Maintains confidentiality Microsoft Office Suite  Accomplishments Revamped the orientation process for all new hires, which was implemented company-wide. Earned special recognition for designing and completing a two-year restructuring project of 20+ years of volunteer records. Received employee of the year for outstanding and dedicated service. Appointed to the Business Processes team - a select group who analyzes and restructures business process for the organization. \n\nEXPERIENCE Company Name City , State HR COORDINATOR 12/2011 to Current Girl Scouts of Gulfcoast Florida is the premier leadership development organization for girls. \nI was brought on board to implement new technology to manage volunteer information, to progress the on-boarding program for newly hired employees and to engage in all aspects of Human Resources.    I was able to improve how the organization manages its volunteer information and approvals by learning, implementing, and training others on a new computer program.   I have successfully overseen the volunteer approval process which includes background screening.  1000+ new volunteers and 1000+ existing volunteers are re-screened each year to ensure a safe environment for girls.  This \n\nEXPERIENCE has provided me with a t horough understanding of background screening laws, required notification, and maintenance of records.  Design new employee packages and send them via mail and e-mail. Resolve personnel issues regarding human resources matters needing clarification, submissions and corrections. Post and audit job postings for old, pending, on-hold and draft positions. Draft department-specific employee announcements. Explain human resources policies and procedures to all employees. Manage communication regarding employee orientation and open enrollment for benefits. Offer consistent payroll disbursement with accurate record keeping of employee PTO and vacation accruals. Process all salary changes stemming from merit increases, promotions, bonuses and pay adjustments. Address inquires from employees and management regarding new-hire activity and ongoing employee relation issues. Work with senior-level management to create fair and consistent HR policies and procedures. Guid clients on how to conduct background checks and verify references. Successfully advanced the on-boarding process by creating a positive, comprehensive new hire \n\nEXPERIENCE; conduct all new hire training; oversee completion of required paperwork and documentation. Manage employee benefits enrollment and termination; comprehensive knowledge of benefit details. Key contributor to the revision of corporate background screening policy, practices, and legal adherence. Company Name City , State HUMAN RESOURCES/OFFICE MANAGER 06/2003 to 04/2011 Conducted benefits administration for benefit-eligible employees. Worked with senior-level management to create fair and consistent HR policies and procedures. Developed an employee handbook, including content and layout. Guided the development and management of HR operations and processes for the organization. Created and managed confidential personnel records. Managed personnel files according to policy and federal and state law and regulations. Generated employee tracking reports each month. Offered consistent payroll disbursement with accurate record keeping of employee PTO and vacation accruals. Managed communication regarding employee orientation and open enrollment for benefits. Resolved personnel issues regarding human resources matters needing clarification, submissions and corrections. Planned and led training programs on staff development. Provided support for CEO and sales team in managing operation work flow. Handled and processed confidential client information. \n\nEDUCATION Master of Arts : Organizational Leadership 2011 Regent University , City , State Minor in Organizational Development Consulting Bachelor of Science : Apparel and Merchandising 1991 Colorado State University , City , State Professional Affiliations Professional development courses completed:  10-week PHR/SPHR preparation course (2013),  Girl Scout University Leadership Series (2014) Professional memberships: Society for Human Resource Management (SHRM) 2009 - 2013, Sarasota Human Resource Association (SHRA) 2010 - 2014,  Founding Member, Zeta Tau Alpha Sorority, Colorado State University \n\nSKILLS Creative problem solving \n\nSKILLS; o rganized with attention to detail; c omputer proficient;  customer service; b enefits; p ayroll; r ecords management; e mployee relations; o n-boarding and training;  HRIS;  MS Office Suite;  ADP and Sage payroll.",
  "education": {
    "degree_level": "master",
    "degree_title": "Master of Arts",
    "field": "Organizational Leadership",
    "year": "2011",
    "institution": "Regent University"
  },
  "work_experience": {
    "job_title": "HR Coordinator",
    "company": "Girl Scouts of Gulfcoast Florida",
    "start_date": "12/2011",
    "end_date": "Current",
    "responsibilities": "Implemented new technology to manage volunteer information and improve onboarding programs. Oversaw volunteer approval and background screening process for over 1000 volunteers annually. Designed employee packages, resolved HR issues, audited job postings, managed employee communication, orientation, and benefits enrollment. Processed payroll and salary changes, and collaborated with management to develop HR policies and procedures."
  },
  "skills": {
    "name": "HR policies and procedures, Employee handbook development, Staff training and development, New employee on-boarding, Off-boarding, Employment law knowledge, Payroll, Benefits administration, Microsoft Office Suite, HRIS, ADP, Sage payroll, Creative problem solving, Customer service, Records management, Employee relations",
    "years_experience": ""
  },
  "language": {
    "name": "",
    "level": ""
  },
  "certifications": {
    "name": "PHR/SPHR preparation course",
    "issuing_organization": "",
    "date_obtained": "2013",
    "valid_until": ""
  },
  "projects": {
    "name": "Volunteer records restructuring project",
    "description": "Designed and completed a two-year restructuring project of 20+ years of volunteer records, improving data management and accuracy.",
    "technologies_used": "",
    "role": "",
    "duration": "2 years"
  },
  "awards": {
    "name": "Employee of the Year",
    "issuing_organization": "Girl Scouts of Gulfcoast Florida",
    "date_received": "",
    "description": "Received for outstanding and dedicated service."
  },
  "voluntary experience": {
    "role": "Founding Member",
    "organization": "Zeta Tau Alpha Sorority, Colorado State University",
    "start_date": "",
    "end_date": "",
    "description": ""
  },
  "publications": {
    "title": "",
    "publication_venue": "",
    "date_published": "",
    "url": ""
  },
  "hobbies": {
    "name": "",
    "description": ""
  },
  "role_fit": "strong",
  "reasoning": "currently works as HR coordinator and has relevant experience"
}